{"id":"5d0n8smj0vbwy6h1kbk7gyb","title":"Window Functions","desc":"","updated":1643227499380,"created":1643227496790,"custom":{},"fname":"s.q.postgres.funcs.window-functions","type":"note","vault":{"fsPath":"DevLog"},"contentHash":"64f720325c13b022899e5e8ba0f10734","links":[{"from":{"fname":"r.{.2022.01.26.sql_for_data_analytics_perform_fast_and_efficient","vaultName":"DevLog"},"type":"backlink","position":{"start":{"line":8,"column":3,"offset":237},"end":{"line":8,"column":42,"offset":276},"indent":[]},"value":"s.q.postgres.funcs.window-functions","alias":"s.q.postgres.funcs.window-functions"}],"anchors":{},"children":[],"parent":"izc530ati922ownwa2dxmql","data":{}}
