{"id":"98hkwm9szucx74somjvd5l1","title":"SNMP","desc":"","updated":1641952492191,"created":1641952397664,"custom":{},"fname":"n.protocol.snmp","type":"note","vault":{"fsPath":"DevLog"},"contentHash":"5e100900adbdf54ed07353a0293db0d6","links":[{"from":{"fname":"s.l.python.libs.pysnmp","vaultName":"DevLog"},"type":"backlink","position":{"start":{"line":3,"column":1,"offset":2},"end":{"line":3,"column":21,"offset":22},"indent":[]},"value":"n.protocol.snmp"}],"anchors":{},"children":["6hdobhbp8dxxu0uwqazyzln","59y4kwcuw77eujqgmyqa8cq"],"parent":"e0468noe3t0enbrez6f88o2","data":{}}
