{"id":"a4hbzhcewdjtgvmwyz2pgy2","title":"Is Safe Integer","desc":"","updated":1641266314221,"created":1641266314221,"custom":{},"fname":"s.l.javascript.es6.numbers.is-safe-integer","type":"note","vault":{"fsPath":"DevLog"},"contentHash":"98a7e91d2a77f39877756052a6d40ef3","links":[],"anchors":{"the-numberissafeinteger-method":{"type":"header","text":"The Number.isSafeInteger() Method","value":"the-numberissafeinteger-method","line":9,"column":0,"depth":2},"example":{"type":"header","text":"Example","value":"example","line":15,"column":0,"depth":3}},"children":[],"parent":"e6dolzh6s9tam1onbi3yg6h","data":{}}
