{"id":"fq75676y72z6f37z0jw9nr6","title":"Classes within Classes","desc":"","updated":1641372091857,"created":1641372091857,"custom":{},"fname":"s.l.cpp.oop.separation-of-concerns.classes-within-classes","type":"note","vault":{"fsPath":"DevLog"},"contentHash":"bafe0a8ac1e0bc025e0e8b9d0e0fb3c1","links":[],"anchors":{"classes-within-classes":{"type":"header","text":"Classes Within Classes","value":"classes-within-classes","line":9,"column":0,"depth":3}},"children":[],"parent":"pjb6kp3n0572hhqr84k2xwe","data":{}}
