{"id":"ido0mim57d5l82mtzri1d3t","title":"Cpp","desc":"","updated":1641371322998,"created":1641105063877,"stub":false,"isDir":true,"custom":{"stub":false,"isDir":true},"fname":"s.l.cpp","type":"note","vault":{"fsPath":"DevLog"},"contentHash":"bfc610ab2dae0688cd04313c8d18aa3e","links":[{"from":{"fname":"s.q.tsql.syntax.comments","vaultName":"DevLog"},"type":"backlink","position":{"start":{"line":3,"column":130,"offset":131},"end":{"line":3,"column":141,"offset":142},"indent":[]},"value":"s.l.cpp","alias":"s.l.cpp"},{"from":{"fname":"s.q.tsql.syntax.operators","vaultName":"DevLog"},"type":"backlink","position":{"start":{"line":20,"column":34,"offset":2483},"end":{"line":20,"column":45,"offset":2494},"indent":[]},"value":"s.l.cpp","alias":"s.l.cpp"}],"anchors":{},"children":["a3ctjzke0uhql49gi6x57mn","hegqgq7va8vanw90lg263eq","fmdaknvnfoz0e7w9uhdo2yf","s6wv5d240qme3ohso4nd9zx","9pbfl810rt62zbyvrp20xmh","pr62tzp4g3n8zw8i85bymur","her8adwj636p8kbm5vapzie","md6b7x4ilth1yp2dh7ri0hz","nyazw5tr3g14gl5sfztv4et","twklb5avgn4s7j7wsw09azv","cnrg8jpu8cm8gdkb6yk8w3r","ut0y32j36nersdfuomciidu","q4a2jfvzx2wrd6evvnfx4fa","rhqhezy9b6ejk8fiuhg6j57","5iafo3gq7vuho3n7ultja9l","zkfh8axyl61wpju2mmb7kez"],"parent":"3z9btu3txu80ibe57hknjfj","data":{},"schema":{"schemaId":"22kslylb5xuk1poc0jou13r","moduleId":"s"}}
