{"id":"ky2wyju62g3gjhhj4fdqnxj","title":"Vim","desc":"","updated":"2022-03-12 2045","created":"2022-03-03 1810","custom":{},"fname":"cli.cmd.vim","type":"note","vault":{"fsPath":"DevLog"},"contentHash":"c82feb00b6742ad5b42666765f4785ca","links":[{"from":{"fname":"log.daily.2021.05.21","vaultName":"DevLog"},"type":"backlink","position":{"start":{"line":2,"column":3,"offset":3},"end":{"line":2,"column":18,"offset":18},"indent":[]},"value":"cli.cmd.vim","alias":"cli.cmd.vim"},{"from":{"fname":"log.daily.2021.06.03","vaultName":"DevLog"},"type":"backlink","position":{"start":{"line":8,"column":139,"offset":846},"end":{"line":8,"column":154,"offset":861},"indent":[]},"value":"cli.cmd.vim","alias":"cli.cmd.vim"},{"from":{"fname":"s.l.python.tips-tricks.underscore-variable","vaultName":"DevLog"},"type":"backlink","position":{"start":{"line":5,"column":122,"offset":144},"end":{"line":5,"column":137,"offset":159},"indent":[]},"value":"cli.cmd.vim","alias":"cli.cmd.vim"}],"anchors":{"created-1641202026932":{"type":"header","text":"created: 1641202026932","value":"created-1641202026932","line":13,"column":0,"depth":2}},"children":["IkmmpQ4eL9amGl3JVOYe1","6491ns751mhkjydjrb05xtw"],"parent":"k1c29v6rspqy2szhzzibpsm","data":{}}
