{"id":"l09l80ykmy6wps89tpllouv","title":"Vars","desc":"","updated":1641427406186,"created":1641427388172,"custom":{},"fname":"s.l.bash.vars","type":"note","vault":{"fsPath":"DevLog"},"contentHash":"10115f7f850c554c4a1323f85638a05a","links":[{"from":{"fname":"s.l.bash.funcs","vaultName":"DevLog"},"type":"backlink","position":{"start":{"line":5,"column":3,"offset":28},"end":{"line":5,"column":20,"offset":45},"indent":[]},"value":"s.l.bash.vars","alias":"s.l.bash.vars"}],"anchors":{"variables":{"type":"header","text":"Variables","value":"variables","line":9,"column":0,"depth":3},"meta-characters-with-variables":{"type":"header","text":"Meta characters with variables","value":"meta-characters-with-variables","line":104,"column":0,"depth":4},"exporting-variables":{"type":"header","text":"Exporting variables","value":"exporting-variables","line":153,"column":0,"depth":4}},"children":[],"parent":"8a6f5aineqilpmdmkc3lked","data":{},"schema":{"schemaId":"np8756j6uwzlkg1n8hsejlu","moduleId":"s"}}
