{"id":"nesfhvsf1doeiydefqj01qa","title":"Zip Function in Python Combine Iterables Together","desc":"","updated":1641270890727,"created":1641168992657,"stub":false,"isDir":false,"custom":{"stub":false,"isDir":false},"fname":"r.+.zip-function-in-python-combine-iterables-together","type":"note","vault":{"fsPath":"DevLog"},"contentHash":"76b8495bf7760faeea83918be096ec8a","links":[{"from":{"fname":"log.daily.2021.09.28","vaultName":"DevLog"},"type":"backlink","position":{"start":{"line":22,"column":3,"offset":835},"end":{"line":22,"column":60,"offset":892},"indent":[]},"value":"r.+.zip-function-in-python-combine-iterables-together","alias":"r.+.zip-function-in-python-combine-iterables-together"}],"anchors":{},"children":[],"parent":"t3g11qc0vpv5vz3id4y0ms9","data":{}}
