{"id":"o1t8el74dr58gu22tblvr3d","title":"389","desc":"","updated":1642144670819,"created":1642144667447,"custom":{},"fname":"n.port.389","type":"note","vault":{"fsPath":"DevLog"},"contentHash":"506be525f4c90af38d4b9aef8f4c9066","links":[{"type":"wiki","from":{"fname":"n.port.389","id":"o1t8el74dr58gu22tblvr3d","vaultName":"DevLog"},"value":"n.protocol.ldap","alias":"n.protocol.ldap","position":{"start":{"line":3,"column":1,"offset":2},"end":{"line":3,"column":20,"offset":21},"indent":[]},"xvault":false,"sameFile":false,"to":{"fname":"n.protocol.ldap"}},{"from":{"fname":"n.protocol.ldap","vaultName":"DevLog"},"type":"backlink","position":{"start":{"line":5,"column":7,"offset":55},"end":{"line":5,"column":21,"offset":69},"indent":[]},"value":"n.port.389","alias":"n.port.389"}],"anchors":{},"children":[],"parent":"f1sihfjh5krd7da5613xbtz","data":{}}
